django_gstorage-0.5.1.dist-info/DESCRIPTION.rst
django_gstorage-0.5.1.dist-info/METADATA
django_gstorage-0.5.1.dist-info/metadata.json
django_gstorage-0.5.1.dist-info/RECORD
django_gstorage-0.5.1.dist-info/top_level.txt
django_gstorage-0.5.1.dist-info/WHEEL
gstorage/__init__.py
gstorage/apps.py
gstorage/bucket.py
gstorage/checks.py
gstorage/constants.py
gstorage/storage.py
gstorage/utils.py
